pywapor/__init__.py
pywapor/et_look.py
pywapor/main.py
pywapor/post_et_look.py
pywapor/pre_et_look.py
pywapor/pre_se_root.py
pywapor/se_root.py
pywapor/collect/__init__.py
pywapor/collect/accounts.py
pywapor/collect/downloader.py
pywapor/collect/product/CHIRPS.py
pywapor/collect/product/COPERNICUS.py
pywapor/collect/product/ERA5.py
pywapor/collect/product/GEOS5.py
pywapor/collect/product/GLO30.txt
pywapor/collect/product/GLO90.txt
pywapor/collect/product/GLOBCOVER.py
pywapor/collect/product/LANDSAT.py
pywapor/collect/product/LSASAF.py
pywapor/collect/product/MERRA2.py
pywapor/collect/product/MODIS.py
pywapor/collect/product/MODIS_tiles.geojson
pywapor/collect/product/SENTINEL2.py
pywapor/collect/product/SENTINEL3.py
pywapor/collect/product/SRTM.py
pywapor/collect/product/SRTM30_tiles.geojson
pywapor/collect/product/STATICS.py
pywapor/collect/product/TERRA.py
pywapor/collect/product/VIIRSL1.py
pywapor/collect/product/__init__.py
pywapor/collect/protocol/__init__.py
pywapor/collect/protocol/cds.py
pywapor/collect/protocol/cog.py
pywapor/collect/protocol/copernicus_odata.py
pywapor/collect/protocol/crawler.py
pywapor/collect/protocol/opendap.py
pywapor/collect/protocol/projections.py
pywapor/configs/WaPOR2_level_1.json
pywapor/configs/WaPOR2_level_2.json
pywapor/configs/WaPOR2_level_3.json
pywapor/configs/WaPOR3_level_2.json
pywapor/configs/WaPOR3_level_3.json
pywapor/configs/all_in.json
pywapor/configs/nrt.json
pywapor/enhancers/__init__.py
pywapor/enhancers/apply_enhancers.py
pywapor/enhancers/dem.py
pywapor/enhancers/gap_fill.py
pywapor/enhancers/lulc.py
pywapor/enhancers/other.py
pywapor/enhancers/pressure.py
pywapor/enhancers/temperature.py
pywapor/enhancers/wind.py
pywapor/enhancers/dms/__init__.py
pywapor/enhancers/dms/pyDMS.py
pywapor/enhancers/dms/pyDMS_utils.py
pywapor/enhancers/dms/thermal_sharpener.py
pywapor/enhancers/smooth/__init__.py
pywapor/enhancers/smooth/archive.py
pywapor/enhancers/smooth/core.py
pywapor/enhancers/smooth/plotters.py
pywapor-3.6.0.dist-info/licenses/LICENSE
pywapor-3.6.0.dist-info/METADATA
pywapor-3.6.0.dist-info/WHEEL
pywapor-3.6.0.dist-info/top_level.txt
pywapor-3.6.0.dist-info/RECORD
