Metadata-Version: 2.4
Name: pywapor
Version: 3.6.0
Home-page: https://www.fao.org/aquastat/py-wapor/
Author: FAO
Author-email: bert.coerver@fao.org
License: Apache
Classifier: Operating System :: OS Independent
Classifier: Programming Language :: Python :: 3.10
Classifier: Programming Language :: Python :: 3.11
Classifier: Programming Language :: Python :: 3.12
Classifier: Programming Language :: Python :: 3.13
Requires-Python: >=3.10
License-File: LICENSE
Requires-Dist: netcdf4
Requires-Dist: gdal<4.0,>=3
Requires-Dist: xarray
Requires-Dist: numpy<2
Requires-Dist: pandas<3
Requires-Dist: requests
Requires-Dist: matplotlib
Requires-Dist: pyproj
Requires-Dist: scipy
Requires-Dist: pycurl
Requires-Dist: joblib
Requires-Dist: bs4
Requires-Dist: rasterio
Requires-Dist: bottleneck
Requires-Dist: tqdm
Requires-Dist: dask
Requires-Dist: rioxarray>=0.15.5
Requires-Dist: cryptography
Requires-Dist: cachetools
Requires-Dist: cdsapi>=0.7.0
Requires-Dist: shapely
Requires-Dist: lxml
Requires-Dist: scikit-learn
Requires-Dist: numba
Requires-Dist: xmltodict
Dynamic: author
Dynamic: author-email
Dynamic: classifier
Dynamic: home-page
Dynamic: license
Dynamic: license-file
Dynamic: requires-dist
Dynamic: requires-python
